midvoxio/__init__.py
midvoxio/config.py
midvoxio/exceptions.py
midvoxio/models.py
midvoxio/parser.py
midvoxio/vox.py
midvoxio/voxio.py
midvoxio/writer.py
midvoxio-0.1.6.dist-info/METADATA
midvoxio-0.1.6.dist-info/WHEEL
midvoxio-0.1.6.dist-info/licenses/LICENSE
midvoxio-0.1.6.dist-info/RECORD
