Metadata-Version: 2.3
Name: midvoxio
Version: 0.1.6
Summary: A python io to load/write/visualize vox files (MagicalVoxel's .vox format).
Project-URL: Homepage, https://github.com/midstreeeam/MidVoxIO
Project-URL: Bug Tracker, https://github.com/midstreeeam/MidVoxIO/issues
Author-email: Midstream <midstream.lou@gmail.com>
License-File: LICENSE
Classifier: License :: OSI Approved :: MIT License
Classifier: Operating System :: OS Independent
Classifier: Programming Language :: Python :: 3
Requires-Python: >=3.7
